pc_skeletor/L1.py
pc_skeletor/__init__.py
pc_skeletor/base.py
pc_skeletor/download.py
pc_skeletor/laplacian.py
pc_skeletor/point2skeleton.py
pc_skeletor/utility.py
pc_skeletor-1.0.0.dist-info/LICENSE
pc_skeletor-1.0.0.dist-info/METADATA
pc_skeletor-1.0.0.dist-info/WHEEL
pc_skeletor-1.0.0.dist-info/top_level.txt
pc_skeletor-1.0.0.dist-info/RECORD
