Metadata-Version: 2.1
Name: pc-skeletor
Version: 1.0.0
Summary: Point Cloud Skeletonizer
Home-page: https://github.com/meyerls/PC-Skeletor
Author: Lukas Meyer
Author-email: lukas.meyer@fau.de
License: MIT
Classifier: Programming Language :: Python :: 3.7
Classifier: Programming Language :: Python :: 3.8
Classifier: Programming Language :: Python :: 3.9
Classifier: Programming Language :: Python :: 3.10
Classifier: License :: OSI Approved :: MIT License
Classifier: Operating System :: OS Independent
License-File: LICENSE
Requires-Dist: mistree (==1.2.0)
Requires-Dist: numpy
Requires-Dist: scipy
Requires-Dist: matplotlib
Requires-Dist: open3d
Requires-Dist: robust-laplacian
Requires-Dist: dgl
Requires-Dist: torch
Requires-Dist: tqdm
Requires-Dist: imageio
Requires-Dist: wget
Requires-Dist: networkx
